socketmap/__init__.py
socketmap/postgres.py
socketmap/socketmap.py
socketmap-0.2.8.dist-info/METADATA
socketmap-0.2.8.dist-info/WHEEL
socketmap-0.2.8.dist-info/top_level.txt
socketmap-0.2.8.dist-info/RECORD
