Metadata-Version: 2.1
Name: socketmap
Version: 0.2.8
Summary: High-level PySpark tool for applying server-dependent functions
Home-page: https://github.com/markrogersjr/socketmap
Author: Mark Rogers
Author-email: m@inmimo.me
License: UNKNOWN
Platform: UNKNOWN
Requires-Dist: psycopg2-binary
